access_specifiers/__init__.py
access_specifiers/access_specifiers.py
access_specifiers-1.5.0.dist-info/METADATA
access_specifiers-1.5.0.dist-info/WHEEL
access_specifiers-1.5.0.dist-info/RECORD
