Metadata-Version: 2.4
Name: access-specifiers
Version: 1.5.0
Summary: Fully featured access modifier library for python
Project-URL: Homepage, https://github.com/pyhacks/access-specifiers
Author-email: pyhacks <enginyildirim111@gmail.com>
Keywords: access,modifier,specifier
Requires-Dist: dill
